typeca/__init__.py
typeca/decorator.py
typeca-1.0.0.dist-info/METADATA
typeca-1.0.0.dist-info/WHEEL
typeca-1.0.0.dist-info/licenses/LICENSE
typeca-1.0.0.dist-info/RECORD
