Metadata-Version: 2.4
Name: typeca
Version: 1.0.0
Summary: A type-checking utility for Python functions
Project-URL: Homepage, https://github.com/GeorgeVictorov/typeca
Project-URL: Issues, https://github.com/GeorgeVictorov/typeca/issues
Author-email: Georgii Viktorov <nowayisleft@gmail.com>
License: Copyright (c) 2024 Georgii Viktorov
License-File: LICENSE
Keywords: decorators,python types,runtime type checking,static typing,type annotations,type checking,type enforcement,type hints,validation
Classifier: License :: OSI Approved :: MIT License
Classifier: Operating System :: OS Independent
Classifier: Programming Language :: Python :: 3
Requires-Python: >=3.10
